custodia.ipa-0.4.2-py3.5-nspkg.pth
custodia/ipa/__init__.py
custodia/ipa/certrequest.py
custodia/ipa/interface.py
custodia/ipa/vault.py
custodia.ipa-0.4.2.dist-info/DESCRIPTION.rst
custodia.ipa-0.4.2.dist-info/METADATA
custodia.ipa-0.4.2.dist-info/RECORD
custodia.ipa-0.4.2.dist-info/WHEEL
custodia.ipa-0.4.2.dist-info/entry_points.txt
custodia.ipa-0.4.2.dist-info/metadata.json
custodia.ipa-0.4.2.dist-info/namespace_packages.txt
custodia.ipa-0.4.2.dist-info/top_level.txt
