Metadata-Version: 2.0
Name: custodia.ipa
Version: 0.4.2
Summary: FreeIPA Vault plugin for Custodia
Home-page: https://github.com/latchset/custodia.ipa
Author: Custodia project Contributors
Author-email: cheimes@redhat.com
License: GPLv3+
Platform: UNKNOWN
Classifier: Development Status :: 4 - Beta
Classifier: Programming Language :: Python :: 2.7
Classifier: Programming Language :: Python :: 3.4
Classifier: Programming Language :: Python :: 3.5
Classifier: Programming Language :: Python :: 3.6
Classifier: Intended Audience :: Developers
Classifier: Topic :: Security
Classifier: Topic :: Software Development :: Libraries :: Python Modules
Requires-Dist: custodia (>=0.5.0)
Requires-Dist: ipalib (>=4.5.0)
Requires-Dist: ipaclient (>=4.5.0)
Requires-Dist: six
Requires-Dist: mock; python_version<"3.3"
Provides-Extra: test
Requires-Dist: coverage; extra == 'test'
Requires-Dist: pytest; extra == 'test'
Provides-Extra: test_docs
Requires-Dist: docutils; extra == 'test_docs'
Requires-Dist: markdown; extra == 'test_docs'
Provides-Extra: test_pep8
Requires-Dist: flake8; extra == 'test_pep8'
Requires-Dist: flake8-import-order; extra == 'test_pep8'
Requires-Dist: pep8-naming; extra == 'test_pep8'
Provides-Extra: test_pylint
Requires-Dist: pylint; extra == 'test_pylint'
Requires-Dist: coverage; extra == 'test_pylint'
Requires-Dist: pytest; extra == 'test_pylint'
